LICENSE
MANIFEST
MANIFEST.in
README.rst
requirements.txt
setup.cfg
setup.py
crawl_requests/__init__.py
crawl_requests/config_UA.py
crawl_requests/config_proxy.py
crawl_requests/req_api.py
crawl_requests/req_default.py
crawl_requests.egg-info/PKG-INFO
crawl_requests.egg-info/SOURCES.txt
crawl_requests.egg-info/dependency_links.txt
crawl_requests.egg-info/not-zip-safe
crawl_requests.egg-info/requires.txt
crawl_requests.egg-info/top_level.txt