Metadata-Version: 1.1
Name: crawl-requests
Version: 2.2.8
Summary: crawl_requests(like requests) can update ua and proxy automatically.
Home-page: https://github.com/shinalone/crawl_requests
Author: UlionTse
Author-email: shinalone@outlook.com
License: MIT
Keywords: requests,crawl_requests
Platform: UNKNOWN
Classifier: Development Status :: 4 - Beta
Classifier: Environment :: Web Environment
Classifier: Intended Audience :: Developers
Classifier: License :: OSI Approved :: MIT License
Classifier: Programming Language :: Python :: 3.4
Classifier: Programming Language :: Python :: 3.5
Classifier: Programming Language :: Python :: 3.6
